{
"user" : {
    "menshoes":[
        {
            "id": 1,
            "name":"adidas Originals Racer TR21",
            "img":"https://i.ebayimg.com/thumbs/images/g/LhgAAOSw5XRj9m~o/s-l300.webp",
            "size": 8,
            "color": "white",
            "price": 100,
            "catagory":"menshoes"
        },
        {
            "id": 2,
            "name": "adidas Originals Swift Run 22",
            "img": "https://i.ebayimg.com/thumbs/images/g/6dAAAOSwnfVj96y-/s-l300.webp",
            "size": 9,
            "color": "black",
            "price": 150,
            "catagory":"menshoes"
        },
        {
            "id": 3,
            "name": "adidas Originals Adilette Clogs",
            "img": "https://i.ebayimg.com/thumbs/images/g/FyMAAOSwxOxj96y~/s-l300.webp",
            "size": 8,
            "color": "black",
            "price": 120,
            "catagory":"menshoes"
        },{
            "id": 4,
            "name": "Nike Air Jordan 1 Mid Ice Blue",
            "img": "https://i.ebayimg.com/thumbs/images/g/BboAAOSw5qxjTiTp/s-l300.webp",
            "size": 9,
            "color": "blue",
            "price": 200,
            "catagory":"menshoes"
        },{
            "id": 5,
            "name": "adidas Originals Grand Court",
            "img": "https://i.ebayimg.com/thumbs/images/g/J38AAOSwtitj9UbE/s-l300.webp",
            "size": 7,
            "color": "black",
            "price": 180,
            "catagory":"menshoes"
        },{
            "id": 6,
            "name": "Puma 37806601 Mens Softride",
            "img": "https://i.ebayimg.com/thumbs/images/g/8qgAAOSwfWpjvGZo/s-l300.webp",
            "size": 8,
            "color": "red",
            "price": 150,
            "catagory":"menshoes"
        },{
            "id": 7,
            "name": "adidas Ultraboost 22 Shoes",
            "img": "https://i.ebayimg.com/thumbs/images/g/nxsAAOSwueBj96zB/s-l300.webp",
            "size": 7,
            "color": "black",
            "price": 140,
            "catagory":"menshoes"
        },{
            "id": 8,
            "name": "Nike Air Max 90 Shoes Blue Chill",
            "img": "https://i.ebayimg.com/thumbs/images/g/a00AAOSwBrtj3UNs/s-l300.webp",
            "size": 8,
            "color": "blue",
            "price": 110,
            "catagory":"menshoes"
        },{
            "id": 9,
            "name": "adidas Originals Swift Run 22",
            "img": "https://i.ebayimg.com/thumbs/images/g/QboAAOSwnX5j9SLs/s-l300.webp",
            "size": 9,
            "color": "blue",
            "price": 150,
            "catagory":"menshoes"
        },{
            "id": 10,
            "name": "adidas Originals NMD_R1 V2",
            "img": "https://i.ebayimg.com/thumbs/images/g/siQAAOSwPFVj9m~n/s-l300.webp",
            "size": 8,
            "color": "white",
            "price": 130,
            "catagory":"menshoes"
        },{
            "id": 11,
            "name": "adidas Daily 3.0 Shoes",
            "img": "https://i.ebayimg.com/thumbs/images/g/04AAAOSwuApj96zE/s-l300.webp",
            "size": 9,
            "color": "white",
            "price": 100,
            "catagory":"menshoes"
        },{
            "id": 12,
            "name": "Puma 192979-03 Mens",
            "img": "https://i.ebayimg.com/thumbs/images/g/5cgAAOSwiVRhW0Tf/s-l300.webp",
            "size": 9,
            "color": "yellow",
            "price": 120,
            "catagory":"menshoes"
        },{
            "id": 13,
            "name": "adidas Originals OZELIA Shoes",
            "img": "https://i.ebayimg.com/thumbs/images/g/t~AAAOSwzG5j9m~p/s-l300.webp",
            "size": 7,
            "color": "yellow",
            "price": 150,
            "catagory":"menshoes"
        },{
            "id": 14,
            "name": "Nike COURT VISION",
            "img": "https://i.ebayimg.com/thumbs/images/g/bswAAOSwIVhjtx0j/s-l300.webp",
            "size": 9,
            "color": "black",
            "price": 170,
            "catagory":"menshoes"
        },{
            "id": 15,
            "name": "NikeCraft General",
            "img": "https://i.ebayimg.com/thumbs/images/g/A5gAAOSwL-1jG7ve/s-l300.webp",
            "size": 9,
            "color": "yellow",
            "price": 130,
            "catagory":"menshoes"
        },
        {
            "id": 16,
            "name": "Keen 1017785K Mens",
            "img": "https://i.ebayimg.com/thumbs/images/g/uIcAAOSwODNjrhuU/s-l300.webp",
            "size": 8,
            "color": "black",
            "price": 140,
            "catagory":"menshoes"
        }
    ],
    "womenshoes":[
        {
            "id": 1,
            "name":"adidas Originals Racer TR21",
            "img":"https://i.ebayimg.com/thumbs/images/g/LhgAAOSw5XRj9m~o/s-l300.webp",
            "size": 8,
            "color": "white",
            "price": 100,
            "catagory":"womenshoes"
        },
        {
            "id": 2,
            "name": "adidas Originals Swift Run 22",
            "img": "https://i.ebayimg.com/thumbs/images/g/6dAAAOSwnfVj96y-/s-l300.webp",
            "size": 9,
            "color": "black",
            "price": 150,
            "catagory":"womenshoes"
        },
        {
            "id": 3,
            "name": "adidas Originals Adilette Clogs",
            "img": "https://i.ebayimg.com/thumbs/images/g/FyMAAOSwxOxj96y~/s-l300.webp",
            "size": 8,
            "color": "black",
            "price": 120,
            "catagory":"womenshoes"
        },{
            "id": 4,
            "name": "Nike Air Jordan 1 Mid Ice Blue",
            "img": "https://i.ebayimg.com/thumbs/images/g/BboAAOSw5qxjTiTp/s-l300.webp",
            "size": 9,
            "color": "blue",
            "price": 200,
            "catagory":"womenshoes"
        },{
            "id": 5,
            "name": "adidas Originals Grand Court",
            "img": "https://i.ebayimg.com/thumbs/images/g/J38AAOSwtitj9UbE/s-l300.webp",
            "size": 7,
            "color": "black",
            "price": 180,
            "catagory":"womenshoes"
        },{
            "id": 6,
            "name": "Puma 37806601 Mens Softride",
            "img": "https://i.ebayimg.com/thumbs/images/g/8qgAAOSwfWpjvGZo/s-l300.webp",
            "size": 8,
            "color": "red",
            "price": 150,
            "catagory":"womenshoes"
        },{
            "id": 7,
            "name": "adidas Ultraboost 22 Shoes",
            "img": "https://i.ebayimg.com/thumbs/images/g/nxsAAOSwueBj96zB/s-l300.webp",
            "size": 7,
            "color": "black",
            "price": 140,
            "catagory":"womenshoes"
        },{
            "id": 8,
            "name": "Nike Air Max 90 Shoes Blue Chill",
            "img": "https://i.ebayimg.com/thumbs/images/g/a00AAOSwBrtj3UNs/s-l300.webp",
            "size": 8,
            "color": "blue",
            "price": 110,
            "catagory":"womenshoes"
        },{
            "id": 9,
            "name": "adidas Originals Swift Run 22",
            "img": "https://i.ebayimg.com/thumbs/images/g/QboAAOSwnX5j9SLs/s-l300.webp",
            "size": 9,
            "color": "blue",
            "price": 150,
            "catagory":"womenshoes"
        },{
            "id": 10,
            "name": "adidas Originals NMD_R1 V2",
            "img": "https://i.ebayimg.com/thumbs/images/g/siQAAOSwPFVj9m~n/s-l300.webp",
            "size": 8,
            "color": "white",
            "price": 130,
            "catagory":"womenshoes"
        },{
            "id": 11,
            "name": "adidas Daily 3.0 Shoes",
            "img": "https://i.ebayimg.com/thumbs/images/g/04AAAOSwuApj96zE/s-l300.webp",
            "size": 9,
            "color": "white",
            "price": 100,
            "catagory":"womenshoes"
        },{
            "id": 12,
            "name": "Puma 192979-03 Mens",
            "img": "https://i.ebayimg.com/thumbs/images/g/5cgAAOSwiVRhW0Tf/s-l300.webp",
            "size": 9,
            "color": "yellow",
            "price": 120,
            "catagory":"womenshoes"
        },{
            "id": 13,
            "name": "adidas Originals OZELIA Shoes",
            "img": "https://i.ebayimg.com/thumbs/images/g/t~AAAOSwzG5j9m~p/s-l300.webp",
            "size": 7,
            "color": "yellow",
            "price": 150,
            "catagory":"womenshoes"
        },{
            "id": 14,
            "name": "Nike COURT VISION",
            "img": "https://i.ebayimg.com/thumbs/images/g/bswAAOSwIVhjtx0j/s-l300.webp",
            "size": 9,
            "color": "black",
            "price": 170,
            "catagory":"womenshoes"
        },{
            "id": 15,
            "name": "NikeCraft General",
            "img": "https://i.ebayimg.com/thumbs/images/g/A5gAAOSwL-1jG7ve/s-l300.webp",
            "size": 9,
            "color": "yellow",
            "price": 130,
            "catagory":"womenshoes"
        },
        {
            "id": 16,
            "name": "Keen 1017785K Mens",
            "img": "https://i.ebayimg.com/thumbs/images/g/uIcAAOSwODNjrhuU/s-l300.webp",
            "size": 8,
            "color": "black",
            "price": 140,
            "catagory":"womenshoes"
        }
    ]
},
"account":[
]
}
